multi_interface/__init__.py
multi_interface/bnd.py
multi_interface/data_provider.py
multi_interface/metrics.py
multi_interface/plt_tools.py
multi_interface/vgg.py
multi_interface/crust1.0/crust1.bnds
multi_interface/crust1.0/crust1.rho
multi_interface/gravities/delta-g-3.dg
multi_interface/gravities/delta-g-5.dg
multi_interface-0.0.3.dist-info/LICENSE.txt
multi_interface-0.0.3.dist-info/METADATA
multi_interface-0.0.3.dist-info/WHEEL
multi_interface-0.0.3.dist-info/top_level.txt
multi_interface-0.0.3.dist-info/RECORD
