Metadata-Version: 2.1
Name: multi-interface
Version: 0.0.3
Summary: reflection and deflection between Crust1.0 and Vertical Gravity Gradient
Home-page: https://github.com/WangChao/Chao-interface
Author: Chao
Requires-Python: >=3.6
License-File: LICENSE.txt
Requires-Dist: matplotlib >=3.8.4
Requires-Dist: numpy >=1.26.4
Requires-Dist: scikit-image >=0.22.0
